Workbook

Sheet Campus Data
A1: Campus | B1: Followers | C1: Signups | D1: Account Status | E1: Signup Rank | F1: Signups per 100 Followers | G1: Estimated Commission | I1: Campus | J1: Signups
A2: Cornell | B2: 486 | C2: 67 | D2: Active | E2: =_xlfn.RANK.EQ(C2,$C$2:$C$13,0) -> 1 | F2: =IFERROR(C2/B2*100,"") -> 13.786008 | G2: =MIN(C2,5)*5+MAX(0,MIN(C2-5,15))*10+MAX(0,C2-20)*15 -> 880 | I2: Cornell | J2: 67
A3: UNC Charlotte | B3: 464 | C3: 47 | D3: Active | E3: =_xlfn.RANK.EQ(C3,$C$2:$C$13,0) -> 6 | F3: =IFERROR(C3/B3*100,"") -> 10.12931 | G3: =MIN(C3,5)*5+MAX(0,MIN(C3-5,15))*10+MAX(0,C3-20)*15 -> 580 | I3: Penn State | J3: 65
A4: Tennessee | B4: 297 | C4: 46 | D4: Active | E4: =_xlfn.RANK.EQ(C4,$C$2:$C$13,0) -> 8 | F4: =IFERROR(C4/B4*100,"") -> 15.488215 | G4: =MIN(C4,5)*5+MAX(0,MIN(C4-5,15))*10+MAX(0,C4-20)*15 -> 565 | I4: Rutgers | J4: 57
A5: Arizona State | B5: 253 | C5: 47 | D5: Active | E5: =_xlfn.RANK.EQ(C5,$C$2:$C$13,0) -> 6 | F5: =IFERROR(C5/B5*100,"") -> 18.577075 | G5: =MIN(C5,5)*5+MAX(0,MIN(C5-5,15))*10+MAX(0,C5-20)*15 -> 580 | I5: Michigan | J5: 54
A6: UCF | B6: 402 | C6: 51 | D6: Active | E6: =_xlfn.RANK.EQ(C6,$C$2:$C$13,0) -> 5 | F6: =IFERROR(C6/B6*100,"") -> 12.686567 | G6: =MIN(C6,5)*5+MAX(0,MIN(C6-5,15))*10+MAX(0,C6-20)*15 -> 640 | I6: UCF | J6: 51
A7: FIU | B7: 57 | C7: 1 | D7: Active | E7: =_xlfn.RANK.EQ(C7,$C$2:$C$13,0) -> 12 | F7: =IFERROR(C7/B7*100,"") -> 1.754386 | G7: =MIN(C7,5)*5+MAX(0,MIN(C7-5,15))*10+MAX(0,C7-20)*15 -> 5 | I7: UNC Charlotte | J7: 47
A8: FSU | B8: 63 | C8: 2 | D8: Active | E8: =_xlfn.RANK.EQ(C8,$C$2:$C$13,0) -> 11 | F8: =IFERROR(C8/B8*100,"") -> 3.1746032 | G8: =MIN(C8,5)*5+MAX(0,MIN(C8-5,15))*10+MAX(0,C8-20)*15 -> 10 | I8: Arizona State | J8: 47
A9: Penn State | C9: 65 | D9: Taken down | E9: =_xlfn.RANK.EQ(C9,$C$2:$C$13,0) -> 2 | F9: =IF(B9="","",IFERROR(C9/B9*100,"")) | G9: =MIN(C9,5)*5+MAX(0,MIN(C9-5,15))*10+MAX(0,C9-20)*15 -> 850 | I9: Tennessee | J9: 46
A10: Michigan | B10: 351 | C10: 54 | D10: Active | E10: =_xlfn.RANK.EQ(C10,$C$2:$C$13,0) -> 4 | F10: =IFERROR(C10/B10*100,"") -> 15.384615 | G10: =MIN(C10,5)*5+MAX(0,MIN(C10-5,15))*10+MAX(0,C10-20)*15 -> 685 | I10: UC Berkeley | J10: 29
A11: Rutgers | B11: 439 | C11: 57 | D11: Active | E11: =_xlfn.RANK.EQ(C11,$C$2:$C$13,0) -> 3 | F11: =IFERROR(C11/B11*100,"") -> 12.984055 | G11: =MIN(C11,5)*5+MAX(0,MIN(C11-5,15))*10+MAX(0,C11-20)*15 -> 730 | I11: Clemson | J11: 6
A12: UC Berkeley | C12: 29 | D12: Taken down | E12: =_xlfn.RANK.EQ(C12,$C$2:$C$13,0) -> 9 | F12: =IF(B12="","",IFERROR(C12/B12*100,"")) | G12: =MIN(C12,5)*5+MAX(0,MIN(C12-5,15))*10+MAX(0,C12-20)*15 -> 310 | I12: FSU | J12: 2
A13: Clemson | C13: 6 | D13: Taken down | E13: =_xlfn.RANK.EQ(C13,$C$2:$C$13,0) -> 10 | F13: =IF(B13="","",IFERROR(C13/B13*100,"")) | G13: =MIN(C13,5)*5+MAX(0,MIN(C13-5,15))*10+MAX(0,C13-20)*15 -> 35 | I13: FIU | J13: 1

Sheet Growth Dashboard
A1: Courselynx Growth & Operations Dashboard
A3: Total Signups | B3: =SUM('Campus Data'!C2:C13) -> 472 | D3: Total Campuses | E3: =COUNTA('Campus Data'!A2:A13) -> 12
A5: Avg. Signups/Campus | B5: =AVERAGE('Campus Data'!C2:C13) -> 39.333333 | D5: Modeled Commissions | E5: =SUM('Campus Data'!G2:G13) -> 5870
A40: Commission figures are hypothetical estimates based on an assumed tiered incentive structure. They do not represent verified Courselynx expenditures. Signup-to-follower ratios are descriptive and should not be interpreted as conversion rates.

Sheet Cost Analysis
A1: Campus | B1: Signups | C1: Modeled Commission | D1: Modeled Cost per Signup | F1: Campus | G1: Modeled Commission
A2: Cornell | B2: ='Campus Data'!C2 -> 67 | C2: ='Campus Data'!G2 -> 880 | D2: =IFERROR(C2/B2,0) -> 13.134328 | F2: =A2 -> Cornell | G2: =C2 -> 880
A3: Penn State | B3: ='Campus Data'!C9 -> 65 | C3: ='Campus Data'!G9 -> 850 | D3: =IFERROR(C3/B3,0) -> 13.076923 | F3: =A3 -> Penn State | G3: =C3 -> 850
A4: Rutgers | B4: ='Campus Data'!C11 -> 57 | C4: ='Campus Data'!G11 -> 730 | D4: =IFERROR(C4/B4,0) -> 12.807018 | F4: =A4 -> Rutgers | G4: =C4 -> 730
A5: Michigan | B5: ='Campus Data'!C10 -> 54 | C5: ='Campus Data'!G10 -> 685 | D5: =IFERROR(C5/B5,0) -> 12.685185 | F5: =A5 -> Michigan | G5: =C5 -> 685
A6: UCF | B6: ='Campus Data'!C6 -> 51 | C6: ='Campus Data'!G6 -> 640 | D6: =IFERROR(C6/B6,0) -> 12.54902 | F6: =A6 -> UCF | G6: =C6 -> 640
A7: UNC Charlotte | B7: ='Campus Data'!C3 -> 47 | C7: ='Campus Data'!G3 -> 580 | D7: =IFERROR(C7/B7,0) -> 12.340426 | F7: =A7 -> UNC Charlotte | G7: =C7 -> 580
A8: Arizona State | B8: ='Campus Data'!C5 -> 47 | C8: ='Campus Data'!G5 -> 580 | D8: =IFERROR(C8/B8,0) -> 12.340426 | F8: =A8 -> Arizona State | G8: =C8 -> 580
A9: Tennessee | B9: ='Campus Data'!C4 -> 46 | C9: ='Campus Data'!G4 -> 565 | D9: =IFERROR(C9/B9,0) -> 12.282609 | F9: =A9 -> Tennessee | G9: =C9 -> 565
A10: UC Berkeley | B10: ='Campus Data'!C12 -> 29 | C10: ='Campus Data'!G12 -> 310 | D10: =IFERROR(C10/B10,0) -> 10.689655 | F10: =A10 -> UC Berkeley | G10: =C10 -> 310
A11: Clemson | B11: ='Campus Data'!C13 -> 6 | C11: ='Campus Data'!G13 -> 35 | D11: =IFERROR(C11/B11,0) -> 5.8333333 | F11: =A11 -> Clemson | G11: =C11 -> 35
A12: FSU | B12: ='Campus Data'!C8 -> 2 | C12: ='Campus Data'!G8 -> 10 | D12: =IFERROR(C12/B12,0) -> 5 | F12: =A12 -> FSU | G12: =C12 -> 10
A13: FIU | B13: ='Campus Data'!C7 -> 1 | C13: ='Campus Data'!G7 -> 5 | D13: =IFERROR(C13/B13,0) -> 5 | F13: =A13 -> FIU | G13: =C13 -> 5

Sheet Performance Analysis
A1: Campus | B1: Signups | C1: Followers | D1: Signups per 100 Followers | E1: Performance Category
A2: ='Campus Data'!A2 -> Cornell | B2: ='Campus Data'!C2 -> 67 | C2: =IF('Campus Data'!B2="","",'Campus Data'!B2) -> 486 | D2: =IF(C2="","",B2/C2*100) -> 13.786008 | E2: =IF(B2>=50,"High Volume",IF(B2>=20,"Moderate Volume","Low Volume")) -> High Volume
A3: ='Campus Data'!A3 -> UNC Charlotte | B3: ='Campus Data'!C3 -> 47 | C3: =IF('Campus Data'!B3="","",'Campus Data'!B3) -> 464 | D3: =IF(C3="","",B3/C3*100) -> 10.12931 | E3: =IF(B3>=50,"High Volume",IF(B3>=20,"Moderate Volume","Low Volume")) -> Moderate Volume
A4: ='Campus Data'!A4 -> Tennessee | B4: ='Campus Data'!C4 -> 46 | C4: =IF('Campus Data'!B4="","",'Campus Data'!B4) -> 297 | D4: =IF(C4="","",B4/C4*100) -> 15.488215 | E4: =IF(B4>=50,"High Volume",IF(B4>=20,"Moderate Volume","Low Volume")) -> Moderate Volume
A5: ='Campus Data'!A5 -> Arizona State | B5: ='Campus Data'!C5 -> 47 | C5: =IF('Campus Data'!B5="","",'Campus Data'!B5) -> 253 | D5: =IF(C5="","",B5/C5*100) -> 18.577075 | E5: =IF(B5>=50,"High Volume",IF(B5>=20,"Moderate Volume","Low Volume")) -> Moderate Volume
A6: ='Campus Data'!A6 -> UCF | B6: ='Campus Data'!C6 -> 51 | C6: =IF('Campus Data'!B6="","",'Campus Data'!B6) -> 402 | D6: =IF(C6="","",B6/C6*100) -> 12.686567 | E6: =IF(B6>=50,"High Volume",IF(B6>=20,"Moderate Volume","Low Volume")) -> High Volume
A7: ='Campus Data'!A7 -> FIU | B7: ='Campus Data'!C7 -> 1 | C7: =IF('Campus Data'!B7="","",'Campus Data'!B7) -> 57 | D7: =IF(C7="","",B7/C7*100) -> 1.754386 | E7: =IF(B7>=50,"High Volume",IF(B7>=20,"Moderate Volume","Low Volume")) -> Low Volume
A8: ='Campus Data'!A8 -> FSU | B8: ='Campus Data'!C8 -> 2 | C8: =IF('Campus Data'!B8="","",'Campus Data'!B8) -> 63 | D8: =IF(C8="","",B8/C8*100) -> 3.1746032 | E8: =IF(B8>=50,"High Volume",IF(B8>=20,"Moderate Volume","Low Volume")) -> Low Volume
A9: ='Campus Data'!A9 -> Penn State | B9: ='Campus Data'!C9 -> 65 | C9: =IF('Campus Data'!B9="","",'Campus Data'!B9) | D9: =IF(C9="","",B9/C9*100) | E9: =IF(B9>=50,"High Volume",IF(B9>=20,"Moderate Volume","Low Volume")) -> High Volume
A10: ='Campus Data'!A10 -> Michigan | B10: ='Campus Data'!C10 -> 54 | C10: =IF('Campus Data'!B10="","",'Campus Data'!B10) -> 351 | D10: =IF(C10="","",B10/C10*100) -> 15.384615 | E10: =IF(B10>=50,"High Volume",IF(B10>=20,"Moderate Volume","Low Volume")) -> High Volume
A11: ='Campus Data'!A11 -> Rutgers | B11: ='Campus Data'!C11 -> 57 | C11: =IF('Campus Data'!B11="","",'Campus Data'!B11) -> 439 | D11: =IF(C11="","",B11/C11*100) -> 12.984055 | E11: =IF(B11>=50,"High Volume",IF(B11>=20,"Moderate Volume","Low Volume")) -> High Volume
A12: ='Campus Data'!A12 -> UC Berkeley | B12: ='Campus Data'!C12 -> 29 | C12: =IF('Campus Data'!B12="","",'Campus Data'!B12) | D12: =IF(C12="","",B12/C12*100) | E12: =IF(B12>=50,"High Volume",IF(B12>=20,"Moderate Volume","Low Volume")) -> Moderate Volume
A13: ='Campus Data'!A13 -> Clemson | B13: ='Campus Data'!C13 -> 6 | C13: =IF('Campus Data'!B13="","",'Campus Data'!B13) | D13: =IF(C13="","",B13/C13*100) | E13: =IF(B13>=50,"High Volume",IF(B13>=20,"Moderate Volume","Low Volume")) -> Low Volume

Sheet Recommendation
A1: Priority | B1: Campus | C1: Recommendation
A2: High | B2: Arizona State | C2: Investigate successful campaigns behind its high signup-to-follower ratio and test similar approaches at other campuses.
A3: High | B3: Cornell | C3: Maintain growth efforts and evaluate opportunities to expand beyond the current audience.
A4: High | B4: Penn State | C4: Investigate whether restoring the account is feasible given its strong historical signup volume.
A5: Medium | B5: Tennessee | C5: Review its marketing approach and compare it with other moderate-volume campuses.
A6: Medium | B6: FIU & FSU | C6: Diagnose low signup activity before committing additional resources.
A10: Executive Summary
A11: Courselynx recorded 472 signups across 12 campus accounts, averaging 39.3 signups per campus. Cornell led with 67 signups, while Arizona State had the highest reported signups per 100 followers at 18.58. Under a hypothetical tiered commission structure, total modeled commissions were $5,870. The analysis suggests investigating successful approaches at higher-performing campuses, reviewing opportunities to restore discontinued accounts, and diagnosing low signup activity at FIU and FSU before expanding investment.

Sheet Model Assumptions
A1: Assumption | B1: Value | C1: Explanation
A2: Commission Tier 1 | B2: 5 | C2: Applied to signups 1–5 at each campus
A3: Commission Tier 2 | B3: 10 | C3: Applied to signups 6–20 at each campus
A4: Commission Tier 3 | B4: 15 | C4: Applied to signups 21–50 at each campus
A5: Signups Beyond 50 | B5: 15 | C5: Assumed extension of the highest specified commission rate
A6: Qualifying Use | B6: 1 signup = 1 use | C6: Assumption for modeling; actual significant uses may differ
A7: Commission Structure | B7: Marginal | C7: Each rate applies only to signups within its tier
A8: Modeled Costs | B8: Hypothetical | C8: Not verified payments or actual marketing expenses
A9: Follower Data | B9: Reported counts | C9: Missing follower counts remain blank
A10: Signup-to-Follower Ratio | B10: Descriptive metric | C10: Not a true marketing conversion rate

Sheet Scenario Planner
A1: Commission Tier | B1: Current Rate | C1: Proposed Rate | G1: Scenario | H1: Modeled Cost
A2: Signups 1–5 | B2: 5 | C2: 5 | G2: Current Commission Plan | H2: =C20 -> 5870
A3: Signups 6–20 | B3: 10 | C3: 8 | G3: Proposed Commission Plan | H3: =D20 -> 4749
A4: Signups 21+ | B4: 15 | C4: 12
G6: Modeled Saving % | H6: =IFERROR(E20/C20,0) -> 0.19097104
A7: Campus | B7: Signups | C7: Current Cost | D7: Proposed Cost | E7: Savings
A8: ='Campus Data'!A2 -> Cornell | B8: ='Campus Data'!C2 -> 67 | C8: =MIN(B8,5)*$B$2+MAX(0,MIN(B8-5,15))*$B$3+MAX(0,B8-20)*$B$4 -> 880 | D8: =MIN(B8,5)*$C$2+MAX(0,MIN(B8-5,15))*$C$3+MAX(0,B8-20)*$C$4 -> 709 | E8: =C8-D8 -> 171
A9: ='Campus Data'!A3 -> UNC Charlotte | B9: ='Campus Data'!C3 -> 47 | C9: =MIN(B9,5)*$B$2+MAX(0,MIN(B9-5,15))*$B$3+MAX(0,B9-20)*$B$4 -> 580 | D9: =MIN(B9,5)*$C$2+MAX(0,MIN(B9-5,15))*$C$3+MAX(0,B9-20)*$C$4 -> 469 | E9: =C9-D9 -> 111
A10: ='Campus Data'!A4 -> Tennessee | B10: ='Campus Data'!C4 -> 46 | C10: =MIN(B10,5)*$B$2+MAX(0,MIN(B10-5,15))*$B$3+MAX(0,B10-20)*$B$4 -> 565 | D10: =MIN(B10,5)*$C$2+MAX(0,MIN(B10-5,15))*$C$3+MAX(0,B10-20)*$C$4 -> 457 | E10: =C10-D10 -> 108
A11: ='Campus Data'!A5 -> Arizona State | B11: ='Campus Data'!C5 -> 47 | C11: =MIN(B11,5)*$B$2+MAX(0,MIN(B11-5,15))*$B$3+MAX(0,B11-20)*$B$4 -> 580 | D11: =MIN(B11,5)*$C$2+MAX(0,MIN(B11-5,15))*$C$3+MAX(0,B11-20)*$C$4 -> 469 | E11: =C11-D11 -> 111
A12: ='Campus Data'!A6 -> UCF | B12: ='Campus Data'!C6 -> 51 | C12: =MIN(B12,5)*$B$2+MAX(0,MIN(B12-5,15))*$B$3+MAX(0,B12-20)*$B$4 -> 640 | D12: =MIN(B12,5)*$C$2+MAX(0,MIN(B12-5,15))*$C$3+MAX(0,B12-20)*$C$4 -> 517 | E12: =C12-D12 -> 123
A13: ='Campus Data'!A7 -> FIU | B13: ='Campus Data'!C7 -> 1 | C13: =MIN(B13,5)*$B$2+MAX(0,MIN(B13-5,15))*$B$3+MAX(0,B13-20)*$B$4 -> 5 | D13: =MIN(B13,5)*$C$2+MAX(0,MIN(B13-5,15))*$C$3+MAX(0,B13-20)*$C$4 -> 5 | E13: =C13-D13 -> 0
A14: ='Campus Data'!A8 -> FSU | B14: ='Campus Data'!C8 -> 2 | C14: =MIN(B14,5)*$B$2+MAX(0,MIN(B14-5,15))*$B$3+MAX(0,B14-20)*$B$4 -> 10 | D14: =MIN(B14,5)*$C$2+MAX(0,MIN(B14-5,15))*$C$3+MAX(0,B14-20)*$C$4 -> 10 | E14: =C14-D14 -> 0
A15: ='Campus Data'!A9 -> Penn State | B15: ='Campus Data'!C9 -> 65 | C15: =MIN(B15,5)*$B$2+MAX(0,MIN(B15-5,15))*$B$3+MAX(0,B15-20)*$B$4 -> 850 | D15: =MIN(B15,5)*$C$2+MAX(0,MIN(B15-5,15))*$C$3+MAX(0,B15-20)*$C$4 -> 685 | E15: =C15-D15 -> 165
A16: ='Campus Data'!A10 -> Michigan | B16: ='Campus Data'!C10 -> 54 | C16: =MIN(B16,5)*$B$2+MAX(0,MIN(B16-5,15))*$B$3+MAX(0,B16-20)*$B$4 -> 685 | D16: =MIN(B16,5)*$C$2+MAX(0,MIN(B16-5,15))*$C$3+MAX(0,B16-20)*$C$4 -> 553 | E16: =C16-D16 -> 132
A17: ='Campus Data'!A11 -> Rutgers | B17: ='Campus Data'!C11 -> 57 | C17: =MIN(B17,5)*$B$2+MAX(0,MIN(B17-5,15))*$B$3+MAX(0,B17-20)*$B$4 -> 730 | D17: =MIN(B17,5)*$C$2+MAX(0,MIN(B17-5,15))*$C$3+MAX(0,B17-20)*$C$4 -> 589 | E17: =C17-D17 -> 141
A18: ='Campus Data'!A12 -> UC Berkeley | B18: ='Campus Data'!C12 -> 29 | C18: =MIN(B18,5)*$B$2+MAX(0,MIN(B18-5,15))*$B$3+MAX(0,B18-20)*$B$4 -> 310 | D18: =MIN(B18,5)*$C$2+MAX(0,MIN(B18-5,15))*$C$3+MAX(0,B18-20)*$C$4 -> 253 | E18: =C18-D18 -> 57
A19: ='Campus Data'!A13 -> Clemson | B19: ='Campus Data'!C13 -> 6 | C19: =MIN(B19,5)*$B$2+MAX(0,MIN(B19-5,15))*$B$3+MAX(0,B19-20)*$B$4 -> 35 | D19: =MIN(B19,5)*$C$2+MAX(0,MIN(B19-5,15))*$C$3+MAX(0,B19-20)*$C$4 -> 33 | E19: =C19-D19 -> 2
A20: TOTAL | B20: =SUM(B8:B19) -> 472 | C20: =SUM(C8:C19) -> 5870 | D20: =SUM(D8:D19) -> 4749 | E20: =SUM(E8:E19) -> 1121
